{
    "high mcmeal at mcdonalds (or equivalent combo meal)": "high price for a mcmeal",
    "high domestic beer (0.5 liter draught)": "high price for a pint",
    "high water (1.5 liter bottle)": "high price for a water",
    "high cappuccino (regular)": "high price for a cappuccino",
    "high apartment (1 bedroom) in city centre": "high price for a city apartment",
    "high apartment (1 bedroom) outside of centre": "high price for an urban apartment ",
    "high basic (electricity, heating, cooling, water, garbage) for 85m2 apartment": "high price for utilites ",
    "high internet (60 mbps or more, unlimited data, cable/adsl)": "high price for internet",
    "high fitness club, monthly fee for 1 adult": "high price for fitness club",
    "high average monthly net salary (after tax)": "high monthly salary",
    "high cost of living index": "high cost of living",
    "high purchasing power index": "high purchasing power",
    "high safety index": "high safety",
    "high health care index": "good health care",
    "high pollution index": "heavy pollution",
    "high logged gdp per capita": "high gdp per capita",
    "high social support": "good social support",
    "high healthy life expectancy": "high healthy life expectancy",
    "high freedom to make life choices": "high freedom to make life choices",
    "high generosity": "high generosity",
    "high perceptions of corruption": "high perceptions of corruption",
    "high population": "big population",
    "high employment": "high employment",
    "high startup": "good startup scene",
    "high tourism": "much tourism",
    "high housing": "good housing situation",
    "high transport": "good transport infrastructure",
    "high health": "good health system",
    "high food": "good food supply",
    "high internet speed": "good internet speed",
    "high access to contraception": "good access to contraception",
    "high gender equality": "good gender equality",
    "high immigration tolerance": "good immigration tolerance",
    "high lgbt friendly": " lgbt friendly",
    "high nightscene": "good nightscene",
    "high beer": "high beer price indicator",
    "high festival": "good festival scence",
    "high avgtemperature": "high avg temperature",
    "low mcmeal at mcdonalds (or equivalent combo meal)": "low price for a mcmeal",
    "low domestic beer (0.5 liter draught)": "low price for a pint",
    "low water (1.5 liter bottle)": "low price for a water",
    "low cappuccino (regular)": "low price for a cappuccino",
    "low apartment (1 bedroom) in city centre": "low price for a city apartment",
    "low apartment (1 bedroom) outside of centre": "low price for an urban apartment ",
    "low basic (electricity, heating, cooling, water, garbage) for 85m2 apartment": "low price for utilites ",
    "low internet (60 mbps or more, unlimited data, cable/adsl)": "low price for internet",
    "low fitness club, monthly fee for 1 adult": "low price for fitness club",
    "low average monthly net salary (after tax)": "low monthly salary",
    "low cost of living index": "low cost of living",
    "low purchasing power index": "low purchasing power",
    "low safety index": "low safety",
    "low health care index": "bad health care",
    "low pollution index": "little pollution",
    "low logged gdp per capita": "low gdp per capita",
    "low social support": "bad social support",
    "low healthy life expectancy": "low healthy life expectancy",
    "low freedom to make life choices": "low freedom to make life choices",
    "low generosity": "low generosity",
    "low perceptions of corruption": "low perceptions of corruption",
    "low population": "small population",
    "low employment": "low employment",
    "low startup": "bad startup scene",
    "low tourism": "little tourism",
    "low housing": "bad housing situation",
    "low transport": "bad transport infrastructure",
    "low health": "bad health system",
    "low food": "bad food supply",
    "low internet speed": "bad internet speed",
    "low access to contraception": "bad access to contraception",
    "low gender equality": "bad gender equality",
    "low immigration tolerance": "bad immigration tolerance",
    "low lgbt friendly": "not lgbt friendly",
    "low nightscene": "bad nightscene",
    "low beer": "low beer price indicator",
    "low festival": "weak festival scence",
    "low avgtemperature": "low avg temperature"
}